conan2.py
conan2-0.0.4.dist-info/METADATA
conan2-0.0.4.dist-info/WHEEL
conan2-0.0.4.dist-info/entry_points.txt
conan2-0.0.4.dist-info/top_level.txt
conan2-0.0.4.dist-info/RECORD
