Metadata-Version: 2.1
Name: conan2
Version: 0.0.4
Summary: A package for visualizing international tourism of up to 4 countries
Home-page: https://github.com/TogashiAoi/TRIP
Author: aoi togashi
Author-email: atogashi@sciencepark.co.jp
License: UNKNOWN
Project-URL: Bug Tracker, https://github.com/TogashiAoi/TRIP
Platform: UNKNOWN
Classifier: Programming Language :: Python :: 3
Classifier: License :: OSI Approved :: MIT License
Classifier: Operating System :: OS Independent
Requires-Python: >=3.7
